pyx_lang/__init__.py
pyx_lang/__main__.py
pyx_lang/main.py
pyx_lang/hooks/__init__.py
pyx_lang/hooks/_pyx_.py
pyx_lang/importer/__init__.py
pyx_lang/importer/autoinstall.py
pyx_lang/importer/pyx_importer.py
pyx_lang/parser/__init__.py
pyx_lang/parser/_parse.py
pyx_lang/parser/grammar313.txt
pyx_lang/parser/xgrammar313.txt
pyx_lang/parser/compiler/__init__.py
pyx_lang/parser/compiler/ast.py
pyx_lang/parser/compiler/compile.py
pyx_lang/parser/compiler/compile_old.py_old
pyx_lang/parser/tokenizer/__init__.py
pyx_lang/parser/tokenizer/find_pyx_string.py
pyx_lang/parser/tokenizer/token_types.py
pyx_lang/parser/tokenizer/tokenize.py
pyx_lang/parser/tokenizer/tokens.py
hatch_autorun_pyx_lang.pth
pyx_lang-0.1.0.dist-info/METADATA
pyx_lang-0.1.0.dist-info/WHEEL
pyx_lang-0.1.0.dist-info/entry_points.txt
pyx_lang-0.1.0.dist-info/licenses/LICENSE
pyx_lang-0.1.0.dist-info/RECORD
